{
  "directed": false,
  "adjacency": {
    "0": [
      41,
      8,
      2,
      48,
      16
    ],
    "4": [
      48,
      7,
      44,
      35,
      37
    ],
    "7": [
      4,
      1,
      6,
      15,
      16
    ],
    "11": [
      13,
      46,
      42,
      45,
      16
    ],
    "16": [
      7,
      39,
      19,
      0,
      11,
      30
    ],
    "18": [
      13,
      49,
      22,
      6,
      36,
      45
    ],
    "30": [
      22,
      39,
      16,
      2
    ],
    "36": [
      5,
      35,
      18,
      41
    ],
    "37": [
      46,
      4,
      2,
      43
    ],
    "43": [
      37,
      6,
      24,
      17,
      29,
      45
    ],
    "45": [
      11,
      14,
      43,
      18,
      46
    ],
    "41": [
      0,
      36
    ],
    "8": [
      0
    ],
    "2": [
      0,
      30,
      37
    ],
    "48": [
      0,
      4
    ],
    "44": [
      4
    ],
    "35": [
      4,
      36
    ],
    "1": [
      7
    ],
    "6": [
      7,
      18,
      43
    ],
    "15": [
      7
    ],
    "13": [
      11,
      18
    ],
    "46": [
      11,
      37,
      45
    ],
    "42": [
      11
    ],
    "39": [
      16,
      30
    ],
    "19": [
      16
    ],
    "49": [
      18
    ],
    "22": [
      18,
      30
    ],
    "5": [
      36
    ],
    "24": [
      43
    ],
    "17": [
      43
    ],
    "29": [
      43
    ],
    "14": [
      45
    ]
  },
  "node_attrs": {
    "0": {
      "label": "Node_0"
    },
    "4": {
      "label": "Node_4"
    },
    "7": {
      "label": "Node_7"
    },
    "11": {
      "label": "Node_11"
    },
    "16": {
      "label": "Node_16"
    },
    "18": {
      "label": "Node_18"
    },
    "30": {
      "label": "Node_30"
    },
    "36": {
      "label": "Node_36"
    },
    "37": {
      "label": "Node_37"
    },
    "43": {
      "label": "Node_43"
    },
    "45": {
      "label": "Node_45"
    },
    "41": {},
    "8": {},
    "2": {},
    "48": {},
    "44": {},
    "35": {},
    "1": {},
    "6": {},
    "15": {},
    "13": {},
    "46": {},
    "42": {},
    "39": {},
    "19": {},
    "49": {},
    "22": {},
    "5": {},
    "24": {},
    "17": {},
    "29": {},
    "14": {}
  },
  "edge_attrs": {
    "0,41": {
      "weight": 5
    },
    "41,0": {
      "weight": 5
    },
    "0,8": {
      "weight": 4
    },
    "8,0": {
      "weight": 4
    },
    "0,2": {
      "weight": 4
    },
    "2,0": {
      "weight": 4
    },
    "0,48": {
      "weight": 3
    },
    "48,0": {
      "weight": 3
    },
    "4,48": {
      "weight": 2
    },
    "48,4": {
      "weight": 2
    },
    "4,7": {
      "weight": 10
    },
    "7,4": {
      "weight": 10
    },
    "4,44": {
      "weight": 7
    },
    "44,4": {
      "weight": 7
    },
    "4,35": {
      "weight": 1
    },
    "35,4": {
      "weight": 1
    },
    "7,1": {
      "weight": 9
    },
    "1,7": {
      "weight": 9
    },
    "7,6": {
      "weight": 10
    },
    "6,7": {
      "weight": 10
    },
    "7,15": {
      "weight": 1
    },
    "15,7": {
      "weight": 1
    },
    "7,16": {
      "weight": 9
    },
    "16,7": {
      "weight": 9
    },
    "11,13": {
      "weight": 9
    },
    "13,11": {
      "weight": 9
    },
    "11,46": {
      "weight": 7
    },
    "46,11": {
      "weight": 7
    },
    "11,42": {
      "weight": 4
    },
    "42,11": {
      "weight": 4
    },
    "11,45": {
      "weight": 8
    },
    "45,11": {
      "weight": 8
    },
    "16,39": {
      "weight": 7
    },
    "39,16": {
      "weight": 7
    },
    "16,19": {
      "weight": 6
    },
    "19,16": {
      "weight": 6
    },
    "16,0": {
      "weight": 5
    },
    "0,16": {
      "weight": 5
    },
    "16,11": {
      "weight": 3
    },
    "11,16": {
      "weight": 3
    },
    "18,13": {
      "weight": 2
    },
    "13,18": {
      "weight": 2
    },
    "18,49": {
      "weight": 7
    },
    "49,18": {
      "weight": 7
    },
    "18,22": {
      "weight": 2
    },
    "22,18": {
      "weight": 2
    },
    "18,6": {
      "weight": 6
    },
    "6,18": {
      "weight": 6
    },
    "30,22": {
      "weight": 8
    },
    "22,30": {
      "weight": 8
    },
    "30,39": {
      "weight": 9
    },
    "39,30": {
      "weight": 9
    },
    "30,16": {
      "weight": 2
    },
    "16,30": {
      "weight": 2
    },
    "30,2": {
      "weight": 7
    },
    "2,30": {
      "weight": 7
    },
    "36,5": {
      "weight": 10
    },
    "5,36": {
      "weight": 10
    },
    "36,35": {
      "weight": 6
    },
    "35,36": {
      "weight": 6
    },
    "36,18": {
      "weight": 10
    },
    "18,36": {
      "weight": 10
    },
    "36,41": {
      "weight": 4
    },
    "41,36": {
      "weight": 4
    },
    "37,46": {
      "weight": 4
    },
    "46,37": {
      "weight": 4
    },
    "37,4": {
      "weight": 5
    },
    "4,37": {
      "weight": 5
    },
    "37,2": {
      "weight": 2
    },
    "2,37": {
      "weight": 2
    },
    "37,43": {
      "weight": 4
    },
    "43,37": {
      "weight": 4
    },
    "43,6": {
      "weight": 6
    },
    "6,43": {
      "weight": 6
    },
    "43,24": {
      "weight": 3
    },
    "24,43": {
      "weight": 3
    },
    "43,17": {
      "weight": 6
    },
    "17,43": {
      "weight": 6
    },
    "43,29": {
      "weight": 6
    },
    "29,43": {
      "weight": 6
    },
    "45,14": {
      "weight": 2
    },
    "14,45": {
      "weight": 2
    },
    "45,43": {
      "weight": 10
    },
    "43,45": {
      "weight": 10
    },
    "45,18": {
      "weight": 3
    },
    "18,45": {
      "weight": 3
    },
    "45,46": {
      "weight": 9
    },
    "46,45": {
      "weight": 9
    }
  }
}